freetier.py
cyberrazor-0.2.0.dist-info/METADATA
cyberrazor-0.2.0.dist-info/WHEEL
cyberrazor-0.2.0.dist-info/top_level.txt
cyberrazor-0.2.0.dist-info/RECORD
