Metadata-Version: 2.4
Name: cyberrazor
Version: 0.2.0
Summary: A package created by Gemini.
Author: Gemini
Author-email: gemini@google.com
Dynamic: author
Dynamic: author-email
Dynamic: summary
